Metadata-Version: 2.1
Name: TestNewBao
Version: 0.4
Summary: 包的概述
Author: 吴儒林
Author-email: 946317637@qq.com
